[
  {
    "id": "82927092B39502170322116",
    "name": "Provincia de Bocas del Toro"
  },
  {
    "id": "82927092B18334008327541",
    "name": "Colón Province"
  },
  {
    "id": "82927092B49726656591260",
    "name": "Provincia de Darién"
  },
  {
    "id": "82927092B81098200763462",
    "name": "Comarca Emberá-Wounaan"
  },
  {
    "id": "82927092B30537193423783",
    "name": "Comarca Guna Yala"
  },
  {
    "id": "82927092B31072992504870",
    "name": "Provincia de Herrera"
  },
  {
    "id": "82927092B53100215554732",
    "name": "Provincia de Los Santos"
  },
  {
    "id": "82927092B82997509005914",
    "name": "Comarca Ngäbe-Buglé"
  },
  {
    "id": "82927092B58639026682610",
    "name": "Provincia de Panamá Oeste"
  },
  {
    "id": "82927092B1953206585656",
    "name": "Provincia de Panamá"
  },
  {
    "id": "82927092B39170055747381",
    "name": "Provincia de Veraguas"
  },
  {
    "id": "82927092B1094181974383",
    "name": "Provincia de Chiriquí"
  },
  {
    "id": "82927092B90628020941788",
    "name": "Provincia de Coclé"
  }
]