[
  {
    "id": "36066543B89779678405362",
    "name": "ALBA"
  },
  {
    "id": "36066543B54316219236217",
    "name": "ARAD"
  },
  {
    "id": "36066543B53231297119391",
    "name": "ARGES"
  },
  {
    "id": "36066543B58663638147212",
    "name": "BACAU"
  },
  {
    "id": "36066543B26260700062336",
    "name": "BIHOR"
  },
  {
    "id": "36066543B74561209637266",
    "name": "BISTRITA-NASAUD"
  },
  {
    "id": "36066543B44844051198398",
    "name": "BOTOSANI"
  },
  {
    "id": "36066543B36343129004237",
    "name": "BRAILA"
  },
  {
    "id": "36066543B7969361625805",
    "name": "BRASOV"
  },
  {
    "id": "36066543B78402216072727",
    "name": "BUZAU"
  },
  {
    "id": "36066543B5722188715477",
    "name": "CALARASI"
  },
  {
    "id": "36066543B64946384360033",
    "name": "CARAS-SEVERIN"
  },
  {
    "id": "36066543B42198475713558",
    "name": "CLUJ"
  },
  {
    "id": "36066543B20641671386087",
    "name": "CONSTANTA"
  },
  {
    "id": "36066543B24619858626166",
    "name": "COVASNA"
  },
  {
    "id": "36066543B36508208096212",
    "name": "DAMBOVITA"
  },
  {
    "id": "36066543B77825502227768",
    "name": "DOLJ"
  },
  {
    "id": "36066543B93424276500239",
    "name": "GALATI"
  },
  {
    "id": "36066543B2949768471564",
    "name": "GIURGIU"
  },
  {
    "id": "36066543B9731027217688",
    "name": "GORJ"
  },
  {
    "id": "36066543B14518908529982",
    "name": "HARGHITA"
  },
  {
    "id": "36066543B15225072959052",
    "name": "HUNEDOARA"
  },
  {
    "id": "36066543B9514402375092",
    "name": "IALOMITA"
  },
  {
    "id": "36066543B68152190067022",
    "name": "IASI"
  },
  {
    "id": "36066543B58098055223766",
    "name": "ILFOV"
  },
  {
    "id": "36066543B51562338382257",
    "name": "MARAMURES"
  },
  {
    "id": "36066543B11233778748537",
    "name": "MEHEDINTI"
  },
  {
    "id": "36066543B11747992440272",
    "name": "BUCURESTI"
  },
  {
    "id": "36066543B31003852704017",
    "name": "MURES"
  },
  {
    "id": "36066543B92634150337313",
    "name": "NEAMT"
  },
  {
    "id": "36066543B87560711020488",
    "name": "OLT"
  },
  {
    "id": "36066543B96905451171357",
    "name": "PRAHOVA"
  },
  {
    "id": "36066543B8882897274660",
    "name": "SALAJ"
  },
  {
    "id": "36066543B37248446823778",
    "name": "SATU MARE"
  },
  {
    "id": "36066543B78296944586190",
    "name": "SIBIU"
  },
  {
    "id": "36066543B72359943930714",
    "name": "SUCEAVA"
  },
  {
    "id": "36066543B97406375074903",
    "name": "TELEORMAN"
  },
  {
    "id": "36066543B49718248736475",
    "name": "TIMIS"
  },
  {
    "id": "36066543B86483735073728",
    "name": "TULCEA"
  },
  {
    "id": "36066543B39156092034573",
    "name": "VALCEA"
  },
  {
    "id": "36066543B98418194735101",
    "name": "VASLUI"
  },
  {
    "id": "36066543B45061076601041",
    "name": "VRANCEA"
  }
]