[
  {
    "id": "40696546B36446689180219",
    "name": "A'ana"
  },
  {
    "id": "40696546B9385579031596",
    "name": "Aiga-i-le-Tai"
  },
  {
    "id": "40696546B40781349975951",
    "name": "Atua"
  },
  {
    "id": "40696546B94827234951055",
    "name": "Fa'asaleleage"
  },
  {
    "id": "40696546B45584224409911",
    "name": "Gaga'emauga"
  },
  {
    "id": "40696546B1701315009328",
    "name": "Gaga'ifomauga"
  },
  {
    "id": "40696546B72194673836531",
    "name": "Palauli"
  },
  {
    "id": "40696546B5747120083880",
    "name": "Satupa'itea"
  },
  {
    "id": "40696546B29543190564601",
    "name": "Tuamasaga"
  },
  {
    "id": "40696546B90373058224054",
    "name": "Va'a-o-Fonoti"
  },
  {
    "id": "40696546B98223692696505",
    "name": "Vaisigano"
  }
]